maxminddb-3.0.0.dist-info/RECORD
maxminddb-3.0.0.dist-info/WHEEL
maxminddb-3.0.0.dist-info/top_level.txt
maxminddb-3.0.0.dist-info/METADATA
maxminddb-3.0.0.dist-info/licenses/LICENSE
maxminddb/decoder.py
maxminddb/__init__.py
maxminddb/extension.pyi
maxminddb/types.py
maxminddb/reader.py
maxminddb/file.py
maxminddb/py.typed
maxminddb/extension.cpython-311-darwin.so
maxminddb/errors.py
maxminddb/const.py
