Metadata-Version: 2.4
Name: maxminddb
Version: 3.0.0
Summary: Reader for the MaxMind DB format
Author-email: Gregory Oschwald <goschwald@maxmind.com>
License-Expression: Apache-2.0
Project-URL: Homepage, https://www.maxmind.com/
Project-URL: Documentation, https://maxminddb.readthedocs.org/
Project-URL: Source Code, https://github.com/maxmind/MaxMind-DB-Reader-python
Project-URL: Issue Tracker, https://github.com/maxmind/MaxMind-DB-Reader-python/issues
Classifier: Development Status :: 5 - Production/Stable
Classifier: Environment :: Web Environment
Classifier: Intended Audience :: Developers
Classifier: Intended Audience :: System Administrators
Classifier: Programming Language :: Python
Classifier: Programming Language :: Python :: 3
Classifier: Programming Language :: Python :: 3.10
Classifier: Programming Language :: Python :: 3.11
Classifier: Programming Language :: Python :: 3.12
Classifier: Programming Language :: Python :: 3.13
Classifier: Programming Language :: Python :: 3.14
Classifier: Topic :: Internet
Classifier: Topic :: Internet :: Proxy Servers
Requires-Python: >=3.10
License-File: LICENSE
Dynamic: license-file
